gibbsreconstructor/__init__.py
gibbs_reconstructor-1.2.3.dist-info/LICENSE
gibbs_reconstructor-1.2.3.dist-info/LICENSE.txt
gibbs_reconstructor-1.2.3.dist-info/METADATA
gibbs_reconstructor-1.2.3.dist-info/WHEEL
gibbs_reconstructor-1.2.3.dist-info/top_level.txt
gibbs_reconstructor-1.2.3.dist-info/RECORD
