Metadata-Version: 2.1
Name: gibbs-reconstructor
Version: 1.2.3
Summary: Gibbs Reconstruction for linear data reconstruction
Home-page: https://github.com/flheight/gibbs-reconstructor-pypi/
Author: Félix Laplante
Author-email: flheight0@gmail.com
Classifier: Programming Language :: Python :: 3
Classifier: License :: OSI Approved :: MIT License
Classifier: Operating System :: MacOS :: MacOS X
Classifier: Operating System :: Microsoft :: Windows
Classifier: Operating System :: POSIX :: Linux
Requires-Python: >=3.8
License-File: LICENSE
License-File: LICENSE.txt
Requires-Dist: numpy
